{
  "profiles": {
    "coding": {
      "style": "technical",
      "system_prompt": "You are a coding assistant. Preserve code formatting, variable names, and technical terminology. Do not add markdown formatting if not requested."
    },
    "chat": {
      "style": "casual",
      "system_prompt": "You are a casual chat assistant. Use relaxed language, emojis where appropriate, and keep it brief."
    },
    "email": {
      "style": "professional",
      "system_prompt": "You are a professional email assistant. Use formal language, proper salutations, and clear structure."
    },
    "document": {
      "style": "formal",
      "system_prompt": "You are a document writing assistant. Use standard formal English, correct grammar, and clear structure."
    },
    "browser": {
      "style": "neutral",
      "system_prompt": "You are a general writing assistant. Be helpful and clear."
    },
    "default": {
      "style": "neutral",
      "system_prompt": "You are a helpful writing assistant."
    }
  },
  "personas": [
    {
      "id": "developer",
      "name": "Developer",
      "description": "Optimized for coding and technical discussions",
      "icon": "code",
      "settings": {
        "activeModel": "small",
        "styleCategory": "technical",
        "defaultStyle": "technical",
        "flowRefinement": true
      },
      "dictionary": [
        "API", "JSON", "HTML", "CSS", "JavaScript", "TypeScript", "React",
        "Node.js", "npm", "Git", "GitHub", "Docker", "Kubernetes",
        "REST", "GraphQL", "MongoDB", "PostgreSQL", "async", "await"
      ]
    },
    {
      "id": "writer",
      "name": "Writer",
      "description": "Optimized for creative writing and content creation",
      "icon": "edit",
      "settings": {
        "activeModel": "base",
        "styleCategory": "creative",
        "defaultStyle": "eloquent",
        "flowRefinement": true
      },
      "dictionary": [
        "metaphor", "narrative", "protagonist", "antagonist", "dialogue",
        "exposition", "climax", "denouement", "characterization"
      ]
    },
    {
      "id": "executive",
      "name": "Executive",
      "description": "Optimized for business communication",
      "icon": "briefcase",
      "settings": {
        "activeModel": "base",
        "styleCategory": "professional",
        "defaultStyle": "professional",
        "flowRefinement": true
      },
      "dictionary": [
        "ROI", "KPI", "OKR", "stakeholder", "deliverable", "synergy",
        "Q1", "Q2", "Q3", "Q4", "YoY", "MoM", "pipeline", "bandwidth"
      ]
    },
    {
      "id": "casual",
      "name": "Casual",
      "description": "For everyday messaging and social media",
      "icon": "message-circle",
      "settings": {
        "activeModel": "tiny",
        "styleCategory": "casual",
        "defaultStyle": "casual",
        "flowRefinement": false
      },
      "dictionary": []
    }
  ],
  "activePersona": null
}
